{
  "last_update": "2026-04-03",
  "channels_list": [
    {
      "name": "BeIN Sports Full HD (Primary)",
      "url": "https://raw.githubusercontent.com/skndr89/IPTV/master/Bein_Sports.m3u",
      "category": "Sports"
    },
    {
      "name": "Adult Content Global (Pass required in some players)",
      "url": "https://iptv-org.github.io/iptv/categories/adult.m3u",
      "category": "Adult"
    },
    {
      "name": "Hotbird & Astra (European Satellites)",
      "url": "https://raw.githubusercontent.com/bitsurge/iptv-list/master/hotbird.m3u",
      "category": "Europe"
    },
    {
      "name": "Arabsat & Nilesat (Full Arabic)",
      "url": "https://raw.githubusercontent.com/frizzy/iptv/master/nilesat.m3u",
      "category": "Arabic"
    }
  ]
}